{
    "items": [
        {
            "Chinese": "这是什么颜色？",
            "English": "What color is it?",
            "EnglishAudio": "oas_eng_what_color_is_it?",
            "French": null,
            "Image": null,
            "Spanish": "¿DE QUÉ COLOR ES?",
            "SpanishAudio": "oas_spa_de_qué_color_es",
            "chineseaudio": null,
            "frenchaudio": null
        },
        {
            "Chinese": "黑色",
            "English": "black",
            "EnglishAudio": "oas_eng_black",
            "French": null,
            "Image": "negro",
            "Spanish": "negro",
            "SpanishAudio": "oas_spa_negro",
            "chineseaudio": null,
            "frenchaudio": null
        },
        {
            "Chinese": "蓝色",
            "English": "blue",
            "EnglishAudio": "oas_eng_blue",
            "French": null,
            "Image": "azul",
            "Spanish": "azul",
            "SpanishAudio": "oas_spa_azul",
            "chineseaudio": null,
            "frenchaudio": null
        },
        {
            "Chinese": "棕色",
            "English": "brown",
            "EnglishAudio": "oas_eng_brown",
            "French": null,
            "Image": "marron",
            "Spanish": "marrón",
            "SpanishAudio": "oas_spa_marron",
            "chineseaudio": null,
            "frenchaudio": null
        },
        {
            "Chinese": "珊瑚色",
            "English": "coral",
            "EnglishAudio": "oas_eng_coral",
            "French": null,
            "Image": "coral",
            "Spanish": "coralino",
            "SpanishAudio": "oas_spa_coralino",
            "chineseaudio": null,
            "frenchaudio": null
        },
        {
            "Chinese": "金色",
            "English": "gold",
            "EnglishAudio": "oas_eng_gold",
            "French": null,
            "Image": "golden",
            "Spanish": "dorado",
            "SpanishAudio": "oas_spa_dorado",
            "chineseaudio": null,
            "frenchaudio": null
        },
        {
            "Chinese": "灰色",
            "English": "gray",
            "EnglishAudio": "oas_eng_gray",
            "French": null,
            "Image": "gris",
            "Spanish": "gris",
            "SpanishAudio": "oas_spa_gris",
            "chineseaudio": null,
            "frenchaudio": null
        },
        {
            "Chinese": "绿色",
            "English": "green",
            "EnglishAudio": "oas_eng_green",
            "French": null,
            "Image": "verde",
            "Spanish": "verde",
            "SpanishAudio": "oas_spa_verde",
            "chineseaudio": null,
            "frenchaudio": null
        },
        {
            "Chinese": "橙色",
            "English": "orange",
            "EnglishAudio": "oas_eng_orange",
            "French": null,
            "Image": "anaranjado",
            "Spanish": "anaranjado",
            "SpanishAudio": "oas_spa_anaranjado",
            "chineseaudio": null,
            "frenchaudio": null
        },
        {
            "Chinese": "粉红色",
            "English": "pink",
            "EnglishAudio": "oas_eng_pink",
            "French": null,
            "Image": "rosado",
            "Spanish": "rosado",
            "SpanishAudio": "oas_spa_rosado",
            "chineseaudio": null,
            "frenchaudio": null
        },
        {
            "Chinese": "紫色",
            "English": "purple",
            "EnglishAudio": "oas_eng_purple",
            "French": null,
            "Image": "purple",
            "Spanish": "morado",
            "SpanishAudio": "oas_spa_morado",
            "chineseaudio": null,
            "frenchaudio": null
        },
        {
            "Chinese": "红色",
            "English": "red",
            "EnglishAudio": "oas_eng_red",
            "French": null,
            "Image": "red",
            "Spanish": "rojo",
            "SpanishAudio": "oas_spa_rojo",
            "chineseaudio": null,
            "frenchaudio": null
        },
        {
            "Chinese": "银色",
            "English": "silver",
            "EnglishAudio": "oas_eng_silver",
            "French": null,
            "Image": "silver",
            "Spanish": "plateado",
            "SpanishAudio": "oas_spa_plateado",
            "chineseaudio": null,
            "frenchaudio": null
        },
        {
            "Chinese": "绿松石色／蓝绿色",
            "English": "turquoise",
            "EnglishAudio": "oas_eng_turquoise",
            "French": null,
            "Image": "turquoise",
            "Spanish": "turquesa",
            "SpanishAudio": "oas_spa_turquesa",
            "chineseaudio": null,
            "frenchaudio": null
        },
        {
            "Chinese": "紫色",
            "English": "violet",
            "EnglishAudio": "oas_eng_violet",
            "French": null,
            "Image": "violet",
            "Spanish": "violeta",
            "SpanishAudio": "oas_spa_violeta",
            "chineseaudio": null,
            "frenchaudio": null
        },
        {
            "Chinese": "白色",
            "English": "white",
            "EnglishAudio": "oas_eng_white",
            "French": null,
            "Image": "blanco",
            "Spanish": "blanco",
            "SpanishAudio": "oas_spa_blanco",
            "chineseaudio": null,
            "frenchaudio": null
        },
        {
            "Chinese": "黄色",
            "English": "yellow",
            "EnglishAudio": "oas_eng_yellow",
            "French": null,
            "Image": "amarillo",
            "Spanish": "Amarillo",
            "SpanishAudio": "oas_spa_amarillo",
            "chineseaudio": null,
            "frenchaudio": null
        }
    ]
}